tiny_erp/__init__.py
tiny_erp/abstract_models.py
tiny_erp/anza.py
tiny_erp/constants.py
tiny_erp/layout.py
tiny_erp/models.py
tiny_erp/settings.py
tiny_erp/widgets.py
tiny_erp/apps/__init__.py
tiny_erp/apps/locations/__init__.py
tiny_erp/apps/locations/apps.py
tiny_erp/apps/locations/models.py
tiny_erp/apps/locations/migrations/0001_initial.py
tiny_erp/apps/locations/migrations/__init__.py
tiny_erp/apps/products/__init__.py
tiny_erp/apps/products/apps.py
tiny_erp/apps/products/forms.py
tiny_erp/apps/products/models.py
tiny_erp/apps/products/migrations/0001_initial.py
tiny_erp/apps/products/migrations/0002_product_sku.py
tiny_erp/apps/products/migrations/__init__.py
tiny_erp/apps/purchases/__init__.py
tiny_erp/apps/purchases/apps.py
tiny_erp/apps/purchases/emails.py
tiny_erp/apps/purchases/forms.py
tiny_erp/apps/purchases/models.py
tiny_erp/apps/purchases/reviews.py
tiny_erp/apps/purchases/migrations/0001_initial.py
tiny_erp/apps/purchases/migrations/0002_requisitionlineitem_product.py
tiny_erp/apps/purchases/migrations/0003_auto_20200904_2138.py
tiny_erp/apps/purchases/migrations/0004_auto_20200904_2142.py
tiny_erp/apps/purchases/migrations/0005_remove_requisition_comments.py
tiny_erp/apps/purchases/migrations/0006_requisition_review_date.py
tiny_erp/apps/purchases/migrations/__init__.py
tiny_erp/templates/tiny_erp/formset.html
tiny_erp/templates/tiny_erp/product_option.html
tiny_erp/templates/tiny_erp/email/requisition_completed_email_body.html
tiny_erp/templates/tiny_erp/email/requisition_completed_email_body.txt
tiny_erp/templates/tiny_erp/email/requisition_completed_email_subject.txt
tiny_erp/templates/tiny_erp/email/requisition_filed_email_body.html
tiny_erp/templates/tiny_erp/email/requisition_filed_email_body.txt
tiny_erp/templates/tiny_erp/email/requisition_filed_email_subject.txt
django_tiny_erp-0.4.2.dist-info/LICENSE
django_tiny_erp-0.4.2.dist-info/METADATA
django_tiny_erp-0.4.2.dist-info/WHEEL
django_tiny_erp-0.4.2.dist-info/top_level.txt
django_tiny_erp-0.4.2.dist-info/RECORD
