Metadata-Version: 2.1
Name: django-tiny-erp
Version: 0.4.2
Summary: Enterprise Resource Planning (ERP) for tiny companies
Home-page: https://github.com/moshthepitt/tiny-erp
Author: Kelvin Jayanoris
Author-email: kelvin@jayanoris.com
License: MIT
Platform: UNKNOWN
Classifier: Programming Language :: Python
Classifier: Programming Language :: Python :: 3.6
Classifier: Programming Language :: Python :: 3.7
Classifier: Programming Language :: Python :: 3.8
Classifier: Framework :: Django
Classifier: Framework :: Django :: 2.2
Classifier: Framework :: Django :: 3.0
License-File: LICENSE
Requires-Dist: Django (>=2.1.10)
Requires-Dist: django-vega-admin (==0.0.19)
Requires-Dist: small-small-hr (==0.4.2)
Requires-Dist: django-phonenumber-field
Requires-Dist: phonenumbers
Requires-Dist: django-prices
